README.md
setup.cfg
setup.py
dataset/__init__.py
dataset/data_utils.py
dataset/img_reg.py
dataset/load_dataset.py
dataset/tiny_imagenet.py
dataset/transformation.py
gradcam/__init__.py
gradcam/gradcam.py
gradcam/gradcam_pp.py
gradcam/visual.py
models/__init__.py
models/assignment11.py
models/naiveresnet.py
models/networks.py
models/quiz_dnn.py
models/resnet.py
torch_soft.egg-info/PKG-INFO
torch_soft.egg-info/SOURCES.txt
torch_soft.egg-info/dependency_links.txt
torch_soft.egg-info/requires.txt
torch_soft.egg-info/top_level.txt
utils/__init__.py
utils/config.py
utils/lr_finder.py
utils/misc.py
utils/normalization.py
visual/__init__.py
visual/visualization.py